main.py
setup.py
DEADiff.egg-info/PKG-INFO
DEADiff.egg-info/SOURCES.txt
DEADiff.egg-info/dependency_links.txt
DEADiff.egg-info/requires.txt
DEADiff.egg-info/top_level.txt